dynamic_pong/__init__.py
dynamic_pong/__main__.py
dynamic_pong-1.0.8.dist-info/LICENSE
dynamic_pong-1.0.8.dist-info/METADATA
dynamic_pong-1.0.8.dist-info/WHEEL
dynamic_pong-1.0.8.dist-info/entry_points.txt
dynamic_pong-1.0.8.dist-info/top_level.txt
dynamic_pong-1.0.8.dist-info/RECORD
