Metadata-Version: 2.1
Name: dynamic_pong
Version: 1.0.8
Summary: Dynamic Pong: A Python-based modern twist on classic Pong
Author: Adamya Singh
Author-email: <7adamyasingh@gmail.com>
Keywords: python,pong,game,dynamic,resume project,pygame
Classifier: Development Status :: 3 - Alpha
Classifier: Intended Audience :: Developers
Classifier: Programming Language :: Python :: 3
Classifier: Operating System :: Unix
Classifier: Operating System :: MacOS :: MacOS X
Classifier: Operating System :: Microsoft :: Windows
License-File: LICENSE
Requires-Dist: pygame
